{
  "$schema": "../package.schema.json",
  "name": "pkg",
  "description": "A simple package manager for macOS",
  "homepage": "https://pkg.zerolimits.dev",
  "version": "0.3.0",
  "sha256": {
    "macos-arm64": "6695f4385b2ef912324467b7ebe33c5993d8e65bdc1ec5a3eba822de502e6540"
  },
  "url": {
    "macos-arm64": "https://github.com/noClaps/pkg/releases/download/v{{ version }}/pkg.tar.xz"
  },
  "scripts": {
    "install": {
      "macos-arm64": [
        "tar -xf pkg.tar.xz",
        "install pkg {{ pkg.bin_dir }}/pkg"
      ]
    },
    "latest": [
      "gh release list -R noClaps/pkg --json tagName --jq '.[0].tagName' | cut -c 2-"
    ],
    "completions": {
      "macos-arm64": [
        "pkg --completions zsh > {{ pkg.completions.zsh }}/_pkg"
      ]
    }
  }
}
