{
  "$schema": "../package.schema.json",
  "name": "uv",
  "description": "An extremely fast Python package and project manager, written in Rust.",
  "homepage": "https://docs.astral.sh/uv/",
  "version": "0.8.19",
  "sha256": {
    "linux-arm64": "ffd29feed13cdd30b27def8e80e64223325fbe4f7cfc4d4c906ec2531f746bde",
    "linux-x64": "cfc674e9b83d1becfca4d70386e5f7ace4c1fa8c47c518abeebb8ef2b30da4b8",
    "macos-arm64": "bb63d43c40a301d889a985223ee8ce540be199e98b3f27ed8477823869a0a605",
    "macos-x64": "b5f91770e55761b32c9618757ef23ded6671bb9ca0ddf5737eea60dddd493fe9"
  },
  "url": {
    "linux-arm64": "https://github.com/astral-sh/uv/releases/download/{{ version }}/uv-aarch64-unknown-linux-gnu.tar.gz",
    "linux-x64": "https://github.com/astral-sh/uv/releases/download/{{ version }}/uv-x86_64-unknown-linux-gnu.tar.gz",
    "macos-arm64": "https://github.com/astral-sh/uv/releases/download/{{ version }}/uv-aarch64-apple-darwin.tar.gz",
    "macos-x64": "https://github.com/astral-sh/uv/releases/download/{{ version }}/uv-x86_64-apple-darwin.tar.gz"
  },
  "scripts": {
    "install": {
      "linux-arm64": [
        "tar -xf uv-aarch64-unknown-linux-gnu.tar.gz",
        "install uv-aarch64-unknown-linux-gnu/* {{ pkg.bin_dir }}"
      ],
      "linux-x64": [
        "tar -xf uv-x86_64-unknown-linux-gnu.tar.gz",
        "install uv-x86_64-unknown-linux-gnu/* {{ pkg.bin_dir }}"
      ],
      "macos-arm64": [
        "tar -xf uv-aarch64-apple-darwin.tar.gz",
        "install uv-aarch64-apple-darwin/* {{ pkg.bin_dir }}"
      ],
      "macos-x64": [
        "tar -xf uv-x86_64-apple-darwin.tar.gz",
        "install uv-x86_64-apple-darwin/* {{ pkg.bin_dir }}"
      ]
    },
    "latest": [
      "gh release list -R astral-sh/uv --json tagName --jq '.[0].tagName'"
    ],
    "completions": {
      "linux-arm64": [
        "uv generate-shell-completion zsh > {{ pkg.completions.zsh }}/_uv",
        "uvx --generate-shell-completion zsh > {{ pkg.completions.zsh }}/_uvx"
      ],
      "linux-x64": [
        "uv generate-shell-completion zsh > {{ pkg.completions.zsh }}/_uv",
        "uvx --generate-shell-completion zsh > {{ pkg.completions.zsh }}/_uvx"
      ],
      "macos-arm64": [
        "uv generate-shell-completion zsh > {{ pkg.completions.zsh }}/_uv",
        "uvx --generate-shell-completion zsh > {{ pkg.completions.zsh }}/_uvx"
      ],
      "macos-x64": [
        "uv generate-shell-completion zsh > {{ pkg.completions.zsh }}/_uv",
        "uvx --generate-shell-completion zsh > {{ pkg.completions.zsh }}/_uvx"
      ]
    }
  }
}
